ixload/__init__.py
ixload/ixl_app.py
ixload/ixl_hw.py
ixload/ixl_object.py
ixload/ixl_statistics_view.py
ixload/api/IxLoadUtils.py
ixload/api/IxRestUtils.py
ixload/api/__init__.py
ixload/api/ixl_rest.py
pyixload-3.0.3.dist-info/License.txt
pyixload-3.0.3.dist-info/METADATA
pyixload-3.0.3.dist-info/WHEEL
pyixload-3.0.3.dist-info/top_level.txt
pyixload-3.0.3.dist-info/RECORD
