Metadata-Version: 2.1
Name: pyixload
Version: 3.0.3
Summary: Python OO API package to automate Ixia IxLoad traffic generator
Home-page: https://github.com/shmir/PyIxLoad/
Author: Yoram Shamir
Author-email: yoram@ignissoft.com
License: Apache Software License
Keywords: ixload l4l7 test tool ixia automation
Platform: any
Classifier: Development Status :: 5 - Production/Stable
Classifier: Natural Language :: English
Classifier: Topic :: Software Development :: Testing :: Traffic Generation
Classifier: Intended Audience :: Developers
Classifier: License :: OSI Approved :: Apache Software License
Classifier: Operating System :: OS Independent
Classifier: Programming Language :: Python :: 3.7
Classifier: Programming Language :: Python :: 3.8
Requires-Dist: future
Requires-Dist: requests
Requires-Dist: pytrafficgen (<=3.1.0,>3.0.3)
